pythonmoduletest/__init__.py
pythonmoduletest/add.py
pythonmoduletest/subtract.py
pythonmoduletest/extras/__init__.py
pythonmoduletest/extras/divide.py
pythonmoduletest/extras/multiply.py
pythonmoduletest-0.0.2.dist-info/METADATA
pythonmoduletest-0.0.2.dist-info/WHEEL
pythonmoduletest-0.0.2.dist-info/top_level.txt
pythonmoduletest-0.0.2.dist-info/RECORD
