Metadata-Version: 2.1
Name: pythonmoduletest
Version: 0.0.2
Summary: python package install test
Author: CremiyGu
Author-email: shanghainewyork@outlook.com
Keywords: python,install test
Classifier: Development Status :: 3 - Alpha
Classifier: Intended Audience :: Education
Classifier: Programming Language :: Python :: 2
Classifier: Programming Language :: Python :: 3
Classifier: Operating System :: MacOS :: MacOS X 
Classifier: Operating System :: Microsoft :: Windows
